smart_meter_to_openhab/.env.example
smart_meter_to_openhab/__init__.py
smart_meter_to_openhab/interfaces.py
smart_meter_to_openhab/openhab.py
smart_meter_to_openhab/sml_iskra_mt175.py
smart_meter_to_openhab/utils.py
smart_meter_to_openhab_scripts/main.py
smart_meter_to_openhab-0.5.3.dist-info/LICENSE
smart_meter_to_openhab-0.5.3.dist-info/METADATA
smart_meter_to_openhab-0.5.3.dist-info/WHEEL
smart_meter_to_openhab-0.5.3.dist-info/entry_points.txt
smart_meter_to_openhab-0.5.3.dist-info/RECORD
