Metadata-Version: 2.1
Name: smart_meter_to_openhab
Version: 0.5.3
Summary: Pushing data of ISKRA MT175 smart meter to openhab
Home-page: https://github.com/die-bauerei/smart-meter-to-openhab
Author: Heiko Bauer
Author-email: heiko_bauer@icloud.com
Requires-Python: >=3.11,<4.0
Classifier: Programming Language :: Python :: 3
Classifier: Programming Language :: Python :: 3.11
Classifier: Programming Language :: Python :: 3.12
Requires-Dist: pyserial (>=3.5,<4.0)
Requires-Dist: python-dotenv (>=1.0.0,<2.0.0)
Requires-Dist: requests (>=2.31.0,<3.0.0)
Project-URL: Repository, https://github.com/die-bauerei/smart-meter-to-openhab
